mcp_python_client/__init__.py
mcp_python_client/config.py
mcp_python_client/client/__init__.py
mcp_python_client/client/exceptions.py
mcp_python_client/client/mcp_client.py
mcp_python_client/client/utils.py
mcp_python_client-0.1.9.dist-info/METADATA
mcp_python_client-0.1.9.dist-info/WHEEL
mcp_python_client-0.1.9.dist-info/licenses/LICENSE
mcp_python_client-0.1.9.dist-info/RECORD
