Metadata-Version: 2.4
Name: mcp-python-client
Version: 0.1.9
Summary: Python client for interacting with MCP servers and LLMs
Project-URL: Homepage, https://github.com/lingster/mcp-python-client
Project-URL: Bug Tracker, https://github.com/lingster/mcp-python-client/issues
Author-email: Ling Li <email@ling-li.com>
Maintainer-email: Ling Li <email@ling-li.com>
License-File: LICENSE
Classifier: Development Status :: 3 - Alpha
Classifier: Intended Audience :: Developers
Classifier: License :: OSI Approved :: MIT License
Classifier: Operating System :: OS Independent
Classifier: Programming Language :: Python :: 3
Classifier: Programming Language :: Python :: 3.10
Classifier: Programming Language :: Python :: 3.11
Classifier: Topic :: Software Development :: Libraries
Classifier: Topic :: Software Development :: Libraries :: Python Modules
Requires-Python: >=3.10
Requires-Dist: anyio>=4.8.0
Requires-Dist: litellm>=1.63.14
Requires-Dist: loguru>=0.7.3
Requires-Dist: mcp>=0.0.17
Requires-Dist: mypy>=1.15.0
Requires-Dist: pydantic>=2.0.0
Requires-Dist: pytest-asyncio>=0.26.0
Requires-Dist: pytest>=8.3.5
Requires-Dist: python-dotenv>=1.0.0
